hat/asn1/parser.py
hat/asn1/__init__.py
hat/asn1/doc.py
hat/asn1/common.py
hat/asn1/ber.py
hat_asn1-0.7.0.dist-info/LICENSE
hat_asn1-0.7.0.dist-info/METADATA
hat_asn1-0.7.0.dist-info/WHEEL
hat_asn1-0.7.0.dist-info/RECORD
