Metadata-Version: 2.1
Name: hat-asn1
Version: 0.7.0
Summary: Hat ASN.1 parser and encoder
License: Apache-2.0
Classifier: Programming Language :: Python :: 3
Classifier: License :: OSI Approved :: Apache Software License
Provides-Extra: dev
Requires-Dist: hat-json ~=0.6.2
Requires-Dist: hat-peg ~=0.5.10
Requires-Dist: hat-util ~=0.6.19
Requires-Dist: hat-doit ~=0.16.2; extra == 'dev'
Requires-Python: >=3.10
Project-URL: Homepage, http://hat-open.com
Project-URL: Repository, https://github.com/hat-open/hat-asn1.git
Project-URL: Documentation, http://hat-asn1.hat-open.com
